spheroidalwavefunctions.cpython-312-darwin.so
spheroidalwavefunctions-0.1.5.dist-info/RECORD
spheroidalwavefunctions-0.1.5.dist-info/WHEEL
spheroidalwavefunctions-0.1.5.dist-info/license.txt
spheroidalwavefunctions-0.1.5.dist-info/METADATA
