Metadata-Version: 2.1
Name: spheroidalwavefunctions
Version: 0.1.5
Summary: Spheroidal wave functions
Keywords: prolate spheroidal wave function,backscatter,model
Author: Gavin Macaulay
License: MIT License
Classifier: Development Status :: 3 - Alpha
Classifier: Intended Audience :: Science/Research
Classifier: License :: OSI Approved :: MIT License
Classifier: Operating System :: OS Independent
Classifier: Programming Language :: Python :: 3
Classifier: Programming Language :: Python :: 3.9
Classifier: Programming Language :: Python :: 3.10
Classifier: Programming Language :: Python :: 3.11
Classifier: Programming Language :: Python :: 3.12
Classifier: Programming Language :: Python :: 3.13
Classifier: Programming Language :: Python :: 3.14
Classifier: Topic :: Scientific/Engineering
Project-URL: Homepage, https://github.com/gavinmacaulay/spheroidalwavefunctions
Project-URL: Documentation, https://github.com/gavinmacaulay/spheroidalwavefunctions/blob/master/readme.md
Project-URL: Repository, https://github.com/gavinmacaulay/spheroidalwavefunctions
Requires-Python: >=3.9
Requires-Dist: numpy
